{
  "dimension": 2,
  "variables": [
    "AbsEta",
    "Pt"
  ],
  "binning": {
    "x": [
      0.0,
      0.9,
      1.2,
      2.1,
      2.4
    ],
    "y": [
      15.0,
      20.0,
      25.0,
      30.0,
      40.0,
      50.0,
      60.0,
      120.0
    ]
  },
  "data": [
    {
      "bin": [
        0.0,
        0.9
      ],
      "values": [
        {
          "bin": [
            15.0,
            20.0
          ],
          "value": 0.8903100490570068,
          "error_low": 0.001232496230419939,
          "error_high": 0.001232496230419939
        },
        {
          "bin": [
            20.0,
            25.0
          ],
          "value": 0.9228447675704956,
          "error_low": 0.0006143668739066808,
          "error_high": 0.0006143668739066808
        },
        {
          "bin": [
            25.0,
            30.0
          ],
          "value": 0.9511159658432007,
          "error_low": 0.0003130196890970765,
          "error_high": 0.0003130196890970765
        },
        {
          "bin": [
            30.0,
            40.0
          ],
          "value": 0.9761234521865845,
          "error_low": 0.00010121993649397679,
          "error_high": 0.00010121993649397679
        },
        {
          "bin": [
            40.0,
            50.0
          ],
          "value": 0.9902913570404053,
          "error_low": 5.711780016913938e-05,
          "error_high": 5.711780016913938e-05
        },
        {
          "bin": [
            50.0,
            60.0
          ],
          "value": 0.9938045144081116,
          "error_low": 0.00010119816193784177,
          "error_high": 0.00010119816193784177
        },
        {
          "bin": [
            60.0,
            120.0
          ],
          "value": 0.9953382015228271,
          "error_low": 0.00013421236363138808,
          "error_high": 0.00013421236363138808
        }
      ]
    },
    {
      "bin": [
        0.9,
        1.2
      ],
      "values": [
        {
          "bin": [
            15.0,
            20.0
          ],
          "value": 0.895704448223114,
          "error_low": 0.0018424557230036446,
          "error_high": 0.0018424557230036446
        },
        {
          "bin": [
            20.0,
            25.0
          ],
          "value": 0.9268714189529419,
          "error_low": 0.001020545426914202,
          "error_high": 0.001020545426914202
        },
        {
          "bin": [
            25.0,
            30.0
          ],
          "value": 0.9522092938423157,
          "error_low": 0.0005558780196558205,
          "error_high": 0.0005558780196558205
        },
        {
          "bin": [
            30.0,
            40.0
          ],
          "value": 0.9758797287940979,
          "error_low": 0.00018940206836752114,
          "error_high": 0.00018940206836752114
        },
        {
          "bin": [
            40.0,
            50.0
          ],
          "value": 0.9909453392028809,
          "error_low": 0.00010317728244732928,
          "error_high": 0.00010317728244732928
        },
        {
          "bin": [
            50.0,
            60.0
          ],
          "value": 0.9937736392021179,
          "error_low": 0.00019062094878406261,
          "error_high": 0.00019062094878406261
        },
        {
          "bin": [
            60.0,
            120.0
          ],
          "value": 0.9956608414649963,
          "error_low": 0.00024639529899433206,
          "error_high": 0.00024639529899433206
        }
      ]
    },
    {
      "bin": [
        1.2,
        2.1
      ],
      "values": [
        {
          "bin": [
            15.0,
            20.0
          ],
          "value": 0.8960758447647095,
          "error_low": 0.00095509126937489,
          "error_high": 0.00095509126937489
        },
        {
          "bin": [
            20.0,
            25.0
          ],
          "value": 0.9306685328483582,
          "error_low": 0.0005420068461806526,
          "error_high": 0.0005420068461806526
        },
        {
          "bin": [
            25.0,
            30.0
          ],
          "value": 0.9557365775108337,
          "error_low": 0.0003086217161209749,
          "error_high": 0.0003086217161209749
        },
        {
          "bin": [
            30.0,
            40.0
          ],
          "value": 0.977280855178833,
          "error_low": 0.00011847970418573624,
          "error_high": 0.00011847970418573624
        },
        {
          "bin": [
            40.0,
            50.0
          ],
          "value": 0.9912362098693848,
          "error_low": 6.928842691303878e-05,
          "error_high": 6.928842691303878e-05
        },
        {
          "bin": [
            50.0,
            60.0
          ],
          "value": 0.9944508075714111,
          "error_low": 0.00012378322031350797,
          "error_high": 0.00012378322031350797
        },
        {
          "bin": [
            60.0,
            120.0
          ],
          "value": 0.9956631064414978,
          "error_low": 0.00017179448472092083,
          "error_high": 0.00017179448472092083
        }
      ]
    },
    {
      "bin": [
        2.1,
        2.4
      ],
      "values": [
        {
          "bin": [
            15.0,
            20.0
          ],
          "value": 0.9027361869812012,
          "error_low": 0.001559597053755139,
          "error_high": 0.001559597053755139
        },
        {
          "bin": [
            20.0,
            25.0
          ],
          "value": 0.9352536797523499,
          "error_low": 0.0009277614335486588,
          "error_high": 0.0009277614335486588
        },
        {
          "bin": [
            25.0,
            30.0
          ],
          "value": 0.9602274298667908,
          "error_low": 0.0005358938193824804,
          "error_high": 0.0005358938193824804
        },
        {
          "bin": [
            30.0,
            40.0
          ],
          "value": 0.9794152975082397,
          "error_low": 0.00022368920381763183,
          "error_high": 0.00022368920381763183
        },
        {
          "bin": [
            40.0,
            50.0
          ],
          "value": 0.9919561743736267,
          "error_low": 0.0001525349385745243,
          "error_high": 0.0001525349385745243
        },
        {
          "bin": [
            50.0,
            60.0
          ],
          "value": 0.9946422576904297,
          "error_low": 0.00028069618358724657,
          "error_high": 0.00028069618358724657
        },
        {
          "bin": [
            60.0,
            120.0
          ],
          "value": 0.9958927631378174,
          "error_low": 0.000400539261617099,
          "error_high": 0.000400539261617099
        }
      ]
    }
  ],
  "error_type": "absolute"
}