{
  "dimension": 2,
  "variables": [
    "AbsEta",
    "Pt"
  ],
  "binning": {
    "x": [
      0.0,
      0.9,
      1.2,
      2.1,
      2.4
    ],
    "y": [
      15.0,
      20.0,
      25.0,
      30.0,
      40.0,
      50.0,
      60.0,
      120.0
    ]
  },
  "data": [
    {
      "bin": [
        0.0,
        0.9
      ],
      "values": [
        {
          "bin": [
            15.0,
            20.0
          ],
          "value": 0.9962489008903503,
          "error_low": 0.0008970519821996194,
          "error_high": 0.0008970519821996194
        },
        {
          "bin": [
            20.0,
            25.0
          ],
          "value": 0.9980341196060181,
          "error_low": 0.00039197699952955384,
          "error_high": 0.00039197699952955384
        },
        {
          "bin": [
            25.0,
            30.0
          ],
          "value": 0.996964156627655,
          "error_low": 0.00027347242333551023,
          "error_high": 0.00027347242333551023
        },
        {
          "bin": [
            30.0,
            40.0
          ],
          "value": 0.9971107244491577,
          "error_low": 0.00017035002046639355,
          "error_high": 0.00017035002046639355
        },
        {
          "bin": [
            40.0,
            50.0
          ],
          "value": 0.9969967007637024,
          "error_low": 0.00029004671179208504,
          "error_high": 0.00029004671179208504
        },
        {
          "bin": [
            50.0,
            60.0
          ],
          "value": 0.9964461922645569,
          "error_low": 0.0007383048562610592,
          "error_high": 0.0007383048562610592
        },
        {
          "bin": [
            60.0,
            120.0
          ],
          "value": 0.9966427087783813,
          "error_low": 0.0003800118769991055,
          "error_high": 0.0003800118769991055
        }
      ]
    },
    {
      "bin": [
        0.9,
        1.2
      ],
      "values": [
        {
          "bin": [
            15.0,
            20.0
          ],
          "value": 0.9938026070594788,
          "error_low": 0.0012235542053622471,
          "error_high": 0.0012235542053622471
        },
        {
          "bin": [
            20.0,
            25.0
          ],
          "value": 0.9949729442596436,
          "error_low": 0.0007181130166033601,
          "error_high": 0.0007181130166033601
        },
        {
          "bin": [
            25.0,
            30.0
          ],
          "value": 0.9948208928108215,
          "error_low": 0.0008346572688778371,
          "error_high": 0.0008346572688778371
        },
        {
          "bin": [
            30.0,
            40.0
          ],
          "value": 0.9956531524658203,
          "error_low": 0.00016620406923567487,
          "error_high": 0.00016620406923567487
        },
        {
          "bin": [
            40.0,
            50.0
          ],
          "value": 0.9958726763725281,
          "error_low": 0.00040029259763097797,
          "error_high": 0.00040029259763097797
        },
        {
          "bin": [
            50.0,
            60.0
          ],
          "value": 0.9956191778182983,
          "error_low": 0.0006874402556153225,
          "error_high": 0.0006874402556153225
        },
        {
          "bin": [
            60.0,
            120.0
          ],
          "value": 0.9957872033119202,
          "error_low": 0.0005689780242771834,
          "error_high": 0.0005689780242771834
        }
      ]
    },
    {
      "bin": [
        1.2,
        2.1
      ],
      "values": [
        {
          "bin": [
            15.0,
            20.0
          ],
          "value": 0.994985818862915,
          "error_low": 0.0009558841228108294,
          "error_high": 0.0009558841228108294
        },
        {
          "bin": [
            20.0,
            25.0
          ],
          "value": 0.9953609108924866,
          "error_low": 0.0006791252761168807,
          "error_high": 0.0006791252761168807
        },
        {
          "bin": [
            25.0,
            30.0
          ],
          "value": 0.9951355457305908,
          "error_low": 0.0005664323524585002,
          "error_high": 0.0005664323524585002
        },
        {
          "bin": [
            30.0,
            40.0
          ],
          "value": 0.9957082867622375,
          "error_low": 0.00019756499474257453,
          "error_high": 0.00019756499474257453
        },
        {
          "bin": [
            40.0,
            50.0
          ],
          "value": 0.9960389137268066,
          "error_low": 0.000329795442904645,
          "error_high": 0.000329795442904645
        },
        {
          "bin": [
            50.0,
            60.0
          ],
          "value": 0.9959612488746643,
          "error_low": 0.0005779766407661602,
          "error_high": 0.0005779766407661602
        },
        {
          "bin": [
            60.0,
            120.0
          ],
          "value": 0.9960948824882507,
          "error_low": 0.0008296981326627199,
          "error_high": 0.0008296981326627199
        }
      ]
    },
    {
      "bin": [
        2.1,
        2.4
      ],
      "values": [
        {
          "bin": [
            15.0,
            20.0
          ],
          "value": 0.9898787140846252,
          "error_low": 0.0027106536772383014,
          "error_high": 0.0027106536772383014
        },
        {
          "bin": [
            20.0,
            25.0
          ],
          "value": 0.99046790599823,
          "error_low": 0.0020352005322432087,
          "error_high": 0.0020352005322432087
        },
        {
          "bin": [
            25.0,
            30.0
          ],
          "value": 0.9915432333946228,
          "error_low": 0.001336367984601372,
          "error_high": 0.001336367984601372
        },
        {
          "bin": [
            30.0,
            40.0
          ],
          "value": 0.9917208552360535,
          "error_low": 0.0009135695113574779,
          "error_high": 0.0009135695113574779
        },
        {
          "bin": [
            40.0,
            50.0
          ],
          "value": 0.9921380877494812,
          "error_low": 0.0008017899466748213,
          "error_high": 0.0008017899466748213
        },
        {
          "bin": [
            50.0,
            60.0
          ],
          "value": 0.992568850517273,
          "error_low": 0.0017879444987084628,
          "error_high": 0.0017879444987084628
        },
        {
          "bin": [
            60.0,
            120.0
          ],
          "value": 0.9894170761108398,
          "error_low": 0.0057755317483726195,
          "error_high": 0.0057755317483726195
        }
      ]
    }
  ],
  "error_type": "absolute"
}