{
  "dimension": 2,
  "variables": [
    "AbsEta",
    "Pt"
  ],
  "binning": {
    "x": [
      0.0,
      0.9,
      1.2,
      2.1,
      2.4
    ],
    "y": [
      15.0,
      20.0,
      25.0,
      30.0,
      40.0,
      50.0,
      60.0,
      120.0
    ]
  },
  "data": [
    {
      "bin": [
        0.0,
        0.9
      ],
      "values": [
        {
          "bin": [
            15.0,
            20.0
          ],
          "value": 0.7915973663330078,
          "error_low": 0.0016843342067373727,
          "error_high": 0.0016843342067373727
        },
        {
          "bin": [
            20.0,
            25.0
          ],
          "value": 0.8345221877098083,
          "error_low": 0.0009110033762595933,
          "error_high": 0.0009110033762595933
        },
        {
          "bin": [
            25.0,
            30.0
          ],
          "value": 0.8786022663116455,
          "error_low": 0.0005106076621626446,
          "error_high": 0.0005106076621626446
        },
        {
          "bin": [
            30.0,
            40.0
          ],
          "value": 0.9239347577095032,
          "error_low": 0.00019262638480625023,
          "error_high": 0.00019262638480625023
        },
        {
          "bin": [
            40.0,
            50.0
          ],
          "value": 0.9558137059211731,
          "error_low": 0.00013343307033431245,
          "error_high": 0.00013343307033431245
        },
        {
          "bin": [
            50.0,
            60.0
          ],
          "value": 0.9695646166801453,
          "error_low": 0.00024541541376488284,
          "error_high": 0.00024541541376488284
        },
        {
          "bin": [
            60.0,
            120.0
          ],
          "value": 0.9787635207176208,
          "error_low": 0.00031472890762066814,
          "error_high": 0.00031472890762066814
        }
      ]
    },
    {
      "bin": [
        0.9,
        1.2
      ],
      "values": [
        {
          "bin": [
            15.0,
            20.0
          ],
          "value": 0.7923997044563293,
          "error_low": 0.0025953558998523417,
          "error_high": 0.0025953558998523417
        },
        {
          "bin": [
            20.0,
            25.0
          ],
          "value": 0.8387411236763,
          "error_low": 0.0015410575162408645,
          "error_high": 0.0015410575162408645
        },
        {
          "bin": [
            25.0,
            30.0
          ],
          "value": 0.877711296081543,
          "error_low": 0.0009384792360916643,
          "error_high": 0.0009384792360916643
        },
        {
          "bin": [
            30.0,
            40.0
          ],
          "value": 0.9237117171287537,
          "error_low": 0.00036543898144093383,
          "error_high": 0.00036543898144093383
        },
        {
          "bin": [
            40.0,
            50.0
          ],
          "value": 0.9580534100532532,
          "error_low": 0.00024101550056265434,
          "error_high": 0.00024101550056265434
        },
        {
          "bin": [
            50.0,
            60.0
          ],
          "value": 0.9711984992027283,
          "error_low": 0.00044480294290464125,
          "error_high": 0.00044480294290464125
        },
        {
          "bin": [
            60.0,
            120.0
          ],
          "value": 0.9800333380699158,
          "error_low": 0.0005764547362863207,
          "error_high": 0.0005764547362863207
        }
      ]
    },
    {
      "bin": [
        1.2,
        2.1
      ],
      "values": [
        {
          "bin": [
            15.0,
            20.0
          ],
          "value": 0.8165568709373474,
          "error_low": 0.0013260719480146024,
          "error_high": 0.0013260719480146024
        },
        {
          "bin": [
            20.0,
            25.0
          ],
          "value": 0.8569422960281372,
          "error_low": 0.0008374228687886945,
          "error_high": 0.0008374228687886945
        },
        {
          "bin": [
            25.0,
            30.0
          ],
          "value": 0.8932772278785706,
          "error_low": 0.0005272758136990171,
          "error_high": 0.0005272758136990171
        },
        {
          "bin": [
            30.0,
            40.0
          ],
          "value": 0.9320193529129028,
          "error_low": 0.0002256595787367649,
          "error_high": 0.0002256595787367649
        },
        {
          "bin": [
            40.0,
            50.0
          ],
          "value": 0.9629716277122498,
          "error_low": 0.00015318021633857126,
          "error_high": 0.00015318021633857126
        },
        {
          "bin": [
            50.0,
            60.0
          ],
          "value": 0.9752137064933777,
          "error_low": 0.00027894873208499294,
          "error_high": 0.00027894873208499294
        },
        {
          "bin": [
            60.0,
            120.0
          ],
          "value": 0.9830591082572937,
          "error_low": 0.000361946635498958,
          "error_high": 0.000361946635498958
        }
      ]
    },
    {
      "bin": [
        2.1,
        2.4
      ],
      "values": [
        {
          "bin": [
            15.0,
            20.0
          ],
          "value": 0.8498294353485107,
          "error_low": 0.0021280890685200908,
          "error_high": 0.0021280890685200908
        },
        {
          "bin": [
            20.0,
            25.0
          ],
          "value": 0.8859505653381348,
          "error_low": 0.001366308322088093,
          "error_high": 0.001366308322088093
        },
        {
          "bin": [
            25.0,
            30.0
          ],
          "value": 0.9183176159858704,
          "error_low": 0.0008535371181714621,
          "error_high": 0.0008535371181714621
        },
        {
          "bin": [
            30.0,
            40.0
          ],
          "value": 0.9483770132064819,
          "error_low": 0.00038869422179796165,
          "error_high": 0.00038869422179796165
        },
        {
          "bin": [
            40.0,
            50.0
          ],
          "value": 0.9721868634223938,
          "error_low": 0.00030421843726819467,
          "error_high": 0.00030421843726819467
        },
        {
          "bin": [
            50.0,
            60.0
          ],
          "value": 0.9810421466827393,
          "error_low": 0.0005543480130385178,
          "error_high": 0.0005543480130385178
        },
        {
          "bin": [
            60.0,
            120.0
          ],
          "value": 0.9866062998771667,
          "error_low": 0.0007628855636082455,
          "error_high": 0.0007628855636082455
        }
      ]
    }
  ],
  "error_type": "absolute"
}